setup.py
gist_it.egg-info/PKG-INFO
gist_it.egg-info/SOURCES.txt
gist_it.egg-info/dependency_links.txt
gist_it.egg-info/entry_points.txt
gist_it.egg-info/not-zip-safe
gist_it.egg-info/requires.txt
gist_it.egg-info/top_level.txt
main/__init__.py
main/gist.py
main/github.py
main/main.py