Metadata-Version: 1.1
Name: gist-it
Version: 1.0.5
Summary: Gist_it can send gist
Home-page: https://github.com/gk024kfd/gist_it
Author: se s
Author-email: 3f2j3g02jgw@gmail.com
License: MIT
Platform: UNKNOWN
Classifier: Environment :: Console
Classifier: Intended Audience :: Developers
Classifier: Operating System :: MacOS :: MacOS X
Classifier: Programming Language :: Python
Classifier: Programming Language :: Python :: 2.7
